alteia/__init__.py
alteia/apis/__init__.py
alteia/apis/client/__init__.py
alteia/apis/client/analytics/__init__.py
alteia/apis/client/analytics/analyticsimpl.py
alteia/apis/client/analytics/configurationsimpl.py
alteia/apis/client/analytics/productsimpl.py
alteia/apis/client/annotations/__init__.py
alteia/apis/client/annotations/annotationsimpl.py
alteia/apis/client/auth/__init__.py
alteia/apis/client/auth/companiesimpl.py
alteia/apis/client/auth/oauthclientsimpl.py
alteia/apis/client/auth/sharetokensimpl.py
alteia/apis/client/auth/usersimpl.py
alteia/apis/client/comments/__init__.py
alteia/apis/client/comments/commentsimpl.py
alteia/apis/client/credentials/__init__.py
alteia/apis/client/credentials/credentialsimpl.py
alteia/apis/client/datacapture/__init__.py
alteia/apis/client/datacapture/carriersimpl.py
alteia/apis/client/datacapture/carriersmodelsimpl.py
alteia/apis/client/datacapture/collectiontasksimpl.py
alteia/apis/client/datacapture/pilotsimpl.py
alteia/apis/client/datacapture/sensorsimpl.py
alteia/apis/client/datacapture/sensorsmodelsimpl.py
alteia/apis/client/datacapture/teamsimpl.py
alteia/apis/client/datamngt/__init__.py
alteia/apis/client/datamngt/datasetsimpl.py
alteia/apis/client/datastream/__init__.py
alteia/apis/client/datastream/datastreamassetmonitoredimpl.py
alteia/apis/client/datastream/datastreamsfilesimpl.py
alteia/apis/client/datastream/datastreamsimpl.py
alteia/apis/client/datastreamtemplate/datastreamtemplateimpl.py
alteia/apis/client/featuresservice/__init__.py
alteia/apis/client/featuresservice/collectionsimpl.py
alteia/apis/client/featuresservice/featuresimpl.py
alteia/apis/client/projectmngt/__init__.py
alteia/apis/client/projectmngt/flightsimpl.py
alteia/apis/client/projectmngt/missionsimpl.py
alteia/apis/client/projectmngt/projectsimpl.py
alteia/apis/client/seasonplanner/__init__.py
alteia/apis/client/seasonplanner/assessmentparameterestimationsimpl.py
alteia/apis/client/seasonplanner/assessmentparametervariablesimpl.py
alteia-2.16.1.dist-info/LICENSE
alteia-2.16.1.dist-info/METADATA
alteia-2.16.1.dist-info/WHEEL
alteia-2.16.1.dist-info/RECORD
