Metadata-Version: 2.1
Name: alteia
Version: 2.16.1
Summary: High-level Python interface to Alteia API
Home-page: https://github.com/alteia-ai/alteia-python-sdk
License: MIT
Keywords: sdk,alteia
Author: Alteia Backend team
Author-email: backend-team@alteia.com
Requires-Python: >=3.11,<4.0
Classifier: Development Status :: 5 - Production/Stable
Classifier: Intended Audience :: Developers
Classifier: License :: OSI Approved :: MIT License
Classifier: Programming Language :: Python :: 3
Classifier: Programming Language :: Python :: 3.11
Classifier: Programming Language :: Python :: 3.12
Classifier: Programming Language :: Python :: 3.13
Classifier: Topic :: Software Development :: Build Tools
Provides-Extra: documentation
Requires-Dist: appdirs (>=1.4.3,<2.0.0)
Requires-Dist: docutils (>=0.21.2,<0.22.0)
Requires-Dist: importlib-resources (>=1.4) ; python_version < "3.7"
Requires-Dist: legacy-cgi (>=2.6.1) ; python_full_version > "3.12.0"
Requires-Dist: pathvalidate (>=3.2.1,<4.0.0)
Requires-Dist: recommonmark (>=0.7.1,<0.8.0) ; extra == "documentation"
Requires-Dist: semantic-version (>=2.8.5,<3.0.0)
Requires-Dist: sphinx (>=8.1.3,<9.0.0) ; extra == "documentation"
Requires-Dist: sphinx-autobuild (>=2024.10.3,<2025.0.0) ; extra == "documentation"
Requires-Dist: sphinx_autodoc_typehints (>=2.5.0,<3.0.0) ; extra == "documentation"
Requires-Dist: urllib3 (>=2.2.3,<3.0.0)
Project-URL: Documentation, https://alteia.readthedocs.io/en/latest/index.html
Project-URL: Repository, https://github.com/alteia-ai/alteia-python-sdk
